soccerplots/__init__.py
soccerplots/bumpy_chart.py
soccerplots/radar_chart.py
soccerplots/utils.py
soccerplots-1.0.0.dist-info/LICENSE
soccerplots-1.0.0.dist-info/METADATA
soccerplots-1.0.0.dist-info/WHEEL
soccerplots-1.0.0.dist-info/top_level.txt
soccerplots-1.0.0.dist-info/RECORD
