Metadata-Version: 2.1
Name: soccerplots
Version: 1.0.0
Summary: A Python package for data visualization for football analytics
Home-page: https://github.com/Slothfulwave612/soccerplots
Author: Anmol Durgapal
Author-email: slothfulwave10@gmail.com
License: MIT License
Platform: UNKNOWN
Classifier: License :: OSI Approved :: MIT License
Classifier: Programming Language :: Python :: 3
Classifier: Programming Language :: Python :: 3.7
